authinfo/__init__.py
authinfo-0.0.4.dist-info/METADATA
authinfo-0.0.4.dist-info/WHEEL
authinfo-0.0.4.dist-info/top_level.txt
authinfo-0.0.4.dist-info/RECORD
