Metadata-Version: 2.1
Name: authinfo
Version: 0.0.4
Summary: Parse credentials in ~/.authinfo files, either plain text or GPG-encrypted.
Project-URL: repository, https://gitlab.com/exmakhina/authinfo
